spotipy_types/__init__.py
spotipy_types/_version.py
spotipy_types/models.py
spotipy_types-2025.5.18.dist-info/METADATA
spotipy_types-2025.5.18.dist-info/WHEEL
spotipy_types-2025.5.18.dist-info/licenses/LICENSE
spotipy_types-2025.5.18.dist-info/RECORD
