Metadata-Version: 2.4
Name: spotipy-types
Version: 2025.5.18
Summary: Complete Python type hints for the Spotify Web API using Pydantic models
Project-URL: Homepage, https://github.com/spotipy/spotipy-types
Project-URL: Repository, https://github.com/spotipy/spotipy-types
Project-URL: Issues, https://github.com/spotipy/spotipy-types/issues
Author: Spotipy Types Contributors
License: MIT
License-File: LICENSE
Keywords: openapi,pydantic,spotify,spotipy,types
Classifier: Development Status :: 4 - Beta
Classifier: Intended Audience :: Developers
Classifier: License :: OSI Approved :: MIT License
Classifier: Programming Language :: Python :: 3
Classifier: Programming Language :: Python :: 3.11
Classifier: Programming Language :: Python :: 3.12
Classifier: Programming Language :: Python :: 3.13
Classifier: Topic :: Software Development :: Libraries :: Python Modules
Classifier: Typing :: Typed
Requires-Python: >=3.11
Requires-Dist: pydantic>=2.0.0
Provides-Extra: dev
Requires-Dist: datamodel-code-generator>=0.25.0; extra == 'dev'
Requires-Dist: mypy>=1.0.0; extra == 'dev'
Requires-Dist: pytest>=7.0.0; extra == 'dev'
Requires-Dist: ruff>=0.1.0; extra == 'dev'
